{"templarian":{"name":"Austin Andrews"},"google":{"name":"Google"},"alexefremo":{"name":"Alex Efremo"},"splitbrain":{"name":"Andreas Gohr"},"casesandberg":{"name":"Case Sandberg"},"chrislitherland":{"name":"Chris Litherland"},"diaryofabastard":{"name":"Peter \"Shaggy\" Noble"},"infanf":{"name":"Christopher Schreiner"},"xt3000":{"name":"Cody"},"r3volution11":{"name":"Doug C. Hardester"},"lastrosestudios":{"name":"Gabriel"},"japanyoshilol":{"name":"JapanYoshi"},"eccentric_jay":{"name":"Jay Zawrotny"},"kaifaust":{"name":"Kai Faust"},"krambertech":{"name":"Kateryna Porshnieva"},"kumvert":{"name":"Andy Martinez"},"mririgo":{"name":"Michael Irigoyen"},"mrgrigri":{"name":"Michael Richins"},"rejack89":{"name":"REJack"},"robertogrrraham":{"name":"Roberto Graham"},"_selectlol":{"name":"Augustin Ursu"},"greenturtwig":{"name":"Rowan"},"thunsaker":{"name":"Thomas Hunsaker"},"belledeboheme":{"name":"Yasmina Lembachar"}}